mrsal/amqp/subclass.py
mrsal/basemodels.py
mrsal/config.py
mrsal/exceptions.py
mrsal/superclass.py
mrsal-3.2.0.dist-info/LICENSE.txt
mrsal-3.2.0.dist-info/METADATA
mrsal-3.2.0.dist-info/WHEEL
mrsal-3.2.0.dist-info/RECORD
