Metadata-Version: 2.1
Name: mrsal
Version: 3.2.0
Summary: Production-ready AMQP message broker abstraction with advanced retry logic, dead letter exchanges, and high availability features.
Home-page: https://github.com/NeoMedSys/mrsal
License: GPL-3.0-or-later
Keywords: message broker,RabbitMQ,Pika,Mrsal,AMQP,async,dead letter exchange
Author: Jon E. Nesvold
Author-email: jnesvold@neomedsys.io
Maintainer: Jon E Nesvold
Maintainer-email: jnesvold@neomedsys.io
Requires-Python: >=3.10,<3.13
Classifier: Development Status :: 5 - Production/Stable
Classifier: Intended Audience :: Developers
Classifier: License :: OSI Approved :: GNU General Public License v3 or later (GPLv3+)
Classifier: Operating System :: POSIX :: Linux
Classifier: Programming Language :: Python :: 3
Classifier: Programming Language :: Python :: 3.10
Classifier: Programming Language :: Python :: 3.11
Classifier: Programming Language :: Python :: 3.12
Classifier: Topic :: Communications
Classifier: Topic :: Software Development :: Libraries :: Python Modules
Classifier: Topic :: System :: Networking
Requires-Dist: aio-pika (>=9.4.3,<10.0.0)
Requires-Dist: colorlog (>=6.7.0,<7.0.0)
Requires-Dist: pika (>=1.3.0,<2.0.0)
Requires-Dist: pydantic (>=2.11.5,<3.0.0)
Requires-Dist: retry (>=0.9.2,<0.10.0)
Requires-Dist: tenacity (>=9.0.0,<10.0.0)
Project-URL: Documentation, https://neomedsys.github.io/mrsal/
Project-URL: Repository, https://github.com/NeoMedSys/mrsal
